wxviews/__init__.py
wxviews/app.py
wxviews/containers.py
wxviews/inspection.py
wxviews/menus.py
wxviews/sizers.py
wxviews/styles.py
wxviews/core/__init__.py
wxviews/core/node.py
wxviews/core/pipes.py
wxviews/core/rendering.py
wxviews/widgets/__init__.py
wxviews/widgets/binding.py
wxviews/widgets/rendering.py
wxviews/widgets/setters.py
wxviews-0.8.0.dist-info/LICENSE
wxviews-0.8.0.dist-info/METADATA
wxviews-0.8.0.dist-info/WHEEL
wxviews-0.8.0.dist-info/top_level.txt
wxviews-0.8.0.dist-info/RECORD
