Metadata-Version: 2.1
Name: wxviews
Version: 0.8.0
Summary: Package for creating wx applications in declarative way.
Project-URL: Homepage, https://github.com/eumis/wxviews
Keywords: binding,wxviews,wxpython,pyviews,python,mvvm,wx
Classifier: Development Status :: 3 - Alpha
Classifier: Intended Audience :: Developers
Classifier: Topic :: Software Development :: Libraries
Classifier: License :: OSI Approved :: MIT License
Classifier: Programming Language :: Python :: 3
Classifier: Programming Language :: Python :: 3 :: Only
Classifier: Programming Language :: Python :: 3.6
Classifier: Programming Language :: Python :: 3.7
Classifier: Programming Language :: Python :: 3.8
Classifier: Programming Language :: Python :: 3.9
Classifier: Programming Language :: Python :: 3.10
Requires-Python: >=3.6
License-File: LICENSE
Requires-Dist: pyviews (==4.*)
Requires-Dist: wxPython
